{
    "ImportPassName": "VerilogVerilatorImportPass",
    "verilog_hash": "65e9f5784e4be61052c93821b224d87c3fbd8455a9b8133a7847d7f5a030435213c523c6be31f3d90497b59d75f60df63b754ddd2927f418c5ca1119ffdc5b83",
    "vl_line_trace": false,
    "vl_coverage": false,
    "vl_line_coverage": false,
    "vl_toggle_coverage": false,
    "vl_mk_dir": "obj_dir_HarnessVRTL__n_3__d_0",
    "vl_enable_assert": true,
    "vl_W_lint": true,
    "vl_W_style": true,
    "vl_W_fatal": true,
    "vl_Wno_list": [
        "UNOPTFLAT",
        "UNSIGNED",
        "WIDTH"
    ],
    "vl_xinit": "zeros",
    "vl_trace": true,
    "vl_trace_timescale": "10ps",
    "vl_trace_cycle_time": 100,
    "vl_trace_on_demand": false,
    "vl_trace_on_demand_portname": "",
    "c_flags": "",
    "c_include_path": [],
    "c_srcs": [],
    "ld_flags": "",
    "ld_libs": ""
}